caresurveyor/__init__.py
caresurveyor/cli.py
caresurveyor/core.py
caresurveyor/templates.py
caresurveyor/utils.py
caresurveyor-0.1.1.dist-info/licenses/LICENSE
caresurveyor-0.1.1.dist-info/METADATA
caresurveyor-0.1.1.dist-info/WHEEL
caresurveyor-0.1.1.dist-info/entry_points.txt
caresurveyor-0.1.1.dist-info/top_level.txt
caresurveyor-0.1.1.dist-info/RECORD
